 (cd "$(git rev-parse --show-toplevel)" && git apply --3way <<'EOF' 
diff --git a/main.xml b/main.xml
index 2dca2c796912ebf9067adaed5094654846e582a2..a5101dcad07ce174e032af788fc9efef27034bd5 100644
--- a/main.xml
+++ b/main.xml
@@ -1,25 +1,28 @@
 <?xml version="1.0" encoding="UTF-8"?>
 <mod>
     <info>
         <name>PVM Simple</name>
         <version>1.0.0</version>
         <author>user12342143</author>
         <description>A lightweight Lua-based viewmodel modification mod with customizable adjustments</description>
         <game>payday2</game>
     </info>
-    
+
     <scripts>
         <script type="lua" path="lua/config.lua" />
+        <script type="lua" path="lua/viewmodel.lua" />
+        <script type="lua" path="lua/menu.lua" />
+        <script type="lua" path="lua/init.lua" />
         <script type="lua" path="lua/pvm_simple.lua" />
     </scripts>
-    
+
     <settings>
         <setting name="enabled" type="bool" default="true" />
         <setting name="position_x" type="slider" min="-100" max="100" default="0" />
         <setting name="position_y" type="slider" min="-100" max="100" default="0" />
         <setting name="position_z" type="slider" min="-100" max="100" default="0" />
         <setting name="rotation_yaw" type="slider" min="-180" max="180" default="0" />
         <setting name="rotation_pitch" type="slider" min="-180" max="180" default="0" />
         <setting name="rotation_roll" type="slider" min="-180" max="180" default="0" />
     </settings>
-</mod>
\ No newline at end of file
+</mod>
 
EOF
)
